data/__init__.py
data/demo/__init__.py
data/login/__init__.py
data/sjfw/__init__.py
data/sjgk/__init__.py
data/sjkf/__init__.py
data_driver/__init__.py
data_driver/yaml_driver.py
key_word/__init__.py
key_word/keyword_web.py
page/__init__.py
page/demo_page0.py
page/login_page/__init__.py
page/login_page/login_page.py
page/login_page/menu_page.py
page/sjfw_page/__init__.py
page/sjfw_page/jkcj_page.py
page/sjfw_page/jkcx_page.py
page/sjfw_page/jksp_page.py
page/sjfw_page/jksxgl_page.py
page/sjfw_page/qxgl_page.py
page/sjfw_page/ywztgl_page.py
page/sjgk_page/__init__.py
page/sjgk_page/fjgl_page.py
page/sjgk_page/flgl_page.py
page/sjgk_page/gzkgl_page.py
page/sjgk_page/lbjk_page.py
page/sjgk_page/sjbzgl_page.py
page/sjgk_page/sjtm_page.py
page/sjgk_page/sjzlgzgl_page.py
page/sjgk_page/tmgl_page.py
page/sjgk_page/tmgz_page.py
page/sjkf_page/__init__.py
page/sjkf_page/ddgl_page.py
test_case/__init__.py
test_case/test_democase/__init__.py
test_case/test_democase/conftest.py
test_case/test_democase/demo.py
test_case/test_democase/test_demo.py
test_case/test_democase/test_demo1.py
test_case/test_democase/test_demodemo.py
test_case/test_democase/test_fix01.py
test_case/test_democase/test_fix02.py
test_case/test_project_sjgk/__init__.py
test_case/test_project_sjgk/test_login/__init__.py
test_case/test_project_sjgk/test_login/conftest.py
test_case/test_project_sjgk/test_login/test_登录.py
test_case/test_project_sjgk/test_sjbz/__init__.py
test_case/test_project_sjgk/test_sjbz/test_09数据标准管理.py
test_case/test_project_sjgk/test_sjbz/test_10落标监控.py
test_case/test_project_sjgk/test_sjfw/__init__.py
test_case/test_project_sjgk/test_sjfw/conftest.py
test_case/test_project_sjgk/test_sjfw/test_01权限管理.py
test_case/test_project_sjgk/test_sjfw/test_02业务主题管理.py
test_case/test_project_sjgk/test_sjfw/test_03接口创建.py
test_case/test_project_sjgk/test_sjfw/test_04接口审批.py
test_case/test_project_sjgk/test_sjfw/test_05接口上线管理.py
test_case/test_project_sjgk/test_sjfw/test_06接口查询.py
yhproject_pkg-0.1.0.dist-info/LICENSE
yhproject_pkg-0.1.0.dist-info/METADATA
yhproject_pkg-0.1.0.dist-info/WHEEL
yhproject_pkg-0.1.0.dist-info/top_level.txt
yhproject_pkg-0.1.0.dist-info/RECORD
