Metadata-Version: 2.1
Name: yhproject-pkg
Version: 0.1.0
Summary: sz-yh-sjgk
Home-page: https://github.com/pypa/sampleproject
Author: HUXIAOFENG
Author-email: 474025548@qq.com
License: UNKNOWN
Platform: UNKNOWN
Classifier: Programming Language :: Python :: 3
Classifier: License :: OSI Approved :: MIT License
Classifier: Operating System :: OS Independent
License-File: LICENSE
